{
  "scraped_at": "2026-07-13T09:38:02.775872",
  "date_range": "2026-07-01 to 2026-08-31",
  "total_events": 45,
  "events": [
    {
      "event_name": "Admissions Activity",
      "date": "June 30",
      "time": "8:00 am - 2:00 am",
      "event_location": "Auditorium D Block by Mr. Abdul Hameed"
    },
    {
      "event_name": "Admissions Activity",
      "date": "July 1",
      "time": "8:00 am - 2:00 am",
      "event_location": "Auditorium D Block by Mr. Abdul Hameed"
    },
    {
      "event_name": "Admissions Activity",
      "date": "July 1",
      "time": "8:00 am - 2:00 am",
      "event_location": "Auditorium D Block by Mr. Abdul Hameed"
    },
    {
      "event_name": "Selection Board",
      "date": "July 1",
      "time": "8:00 am - 5:30 pm",
      "event_location": "109 & 110 BY Mr. Adnan HR"
    },
    {
      "event_name": "Selection Board",
      "date": "July 1",
      "time": "8:30 am - 5:30 pm",
      "event_location": "C-109 & C-110 By Mr. Adnan HR"
    },
    {
      "event_name": "Admissions Activity",
      "date": "July 2",
      "time": "8:00 am - 2:00 am",
      "event_location": "Auditorium D Block by Mr. Abdul Hameed"
    },
    {
      "event_name": "EE Event",
      "date": "July 2",
      "time": "7:00 am - 7:00 pm",
      "event_location": "D Block & A Block Audi by Dr. Saeed"
    },
    {
      "event_name": "Admissions Activity",
      "date": "July 2",
      "time": "8:00 am - 2:00 am",
      "event_location": "Auditorium D Block by Mr. Abdul Hameed"
    },
    {
      "event_name": "CSO Event",
      "date": "July 2",
      "time": "9:00 am - 9:00 pm",
      "event_location": "C-109 by Ms. Laraib"
    },
    {
      "event_name": "Global EXchange Committee Meeting",
      "date": "July 2",
      "time": "10:15 am - 12:45 am",
      "event_location": "MEDC 117 by Ms. Fasiha"
    },
    {
      "event_name": "Admissions Activity",
      "date": "July 3",
      "time": "8:00 am - 2:00 am",
      "event_location": "Auditorium D Block by Mr. Abdul Hameed"
    },
    {
      "event_name": "Global EXchange Committee Meeting",
      "date": "July 3",
      "time": "10:15 am - 12:45 am",
      "event_location": "MEDC 117 by Ms. Fasiha"
    },
    {
      "event_name": "Admissions Activity",
      "date": "July 3",
      "time": "8:00 am - 2:00 am",
      "event_location": "Auditorium D Block by Mr. Abdul Hameed"
    },
    {
      "event_name": "Faculty Meeting",
      "date": "July 3",
      "time": "9:00 am - 1:00 pm",
      "event_location": "MEDC-118 by Ms. Fasiha"
    },
    {
      "event_name": "Admissions Activity",
      "date": "July 4",
      "time": "8:00 am - 2:00 am",
      "event_location": "Auditorium D Block by Mr. Abdul Hameed"
    },
    {
      "event_name": "Admissions Activity",
      "date": "July 4",
      "time": "8:00 am - 2:00 am",
      "event_location": "Auditorium D Block by Mr. Abdul Hameed"
    },
    {
      "event_name": "Admissions Activity",
      "date": "July 5",
      "time": "8:00 am - 2:00 am",
      "event_location": "Auditorium D Block by Mr. Abdul Hameed"
    },
    {
      "event_name": "Admissions Activity",
      "date": "July 5",
      "time": "8:00 am - 2:00 am",
      "event_location": "Auditorium D Block by Mr. Abdul Hameed"
    },
    {
      "event_name": "Admissions Activity",
      "date": "July 6",
      "time": "8:00 am - 2:00 am",
      "event_location": "Auditorium D Block by Mr. Abdul Hameed"
    },
    {
      "event_name": "Admissions Activity",
      "date": "July 6",
      "time": "8:00 am - 2:00 am",
      "event_location": "Auditorium D Block by Mr. Abdul Hameed"
    },
    {
      "event_name": "Course Allocation Meeting",
      "date": "July 6",
      "time": "10:00 am - 12:00 pm",
      "event_location": "CMR by Ms. Fasiha"
    },
    {
      "event_name": "Summer Internship Orientation",
      "date": "July 6",
      "time": "10:00 am - 1:00 pm",
      "event_location": "Auditorium A Block By Zain Khattak CSO"
    },
    {
      "event_name": "Admissions Activity",
      "date": "July 7",
      "time": "8:00 am - 2:00 am",
      "event_location": "Auditorium D Block by Mr. Abdul Hameed"
    },
    {
      "event_name": "Admissions Activity",
      "date": "July 7",
      "time": "8:00 am - 2:00 am",
      "event_location": "Auditorium D Block by Mr. Abdul Hameed"
    },
    {
      "event_name": "Course Allocation Meeting",
      "date": "July 7",
      "time": "9:00 am - 5:00 pm",
      "event_location": "CMR By Ms. Fasiha FSM"
    },
    {
      "event_name": "FSM Seminar",
      "date": "July 7",
      "time": "10:00 am - 2:00 pm",
      "event_location": "MEDC-117 by Ms. Fasiha"
    },
    {
      "event_name": "Admissions Activity",
      "date": "July 8",
      "time": "8:00 am - 2:00 am",
      "event_location": "Auditorium D Block by Mr. Abdul Hameed"
    },
    {
      "event_name": "Admissions Activity",
      "date": "July 8",
      "time": "8:00 am - 2:00 am",
      "event_location": "Auditorium D Block by Mr. Abdul Hameed"
    },
    {
      "event_name": "Admissions Activity",
      "date": "July 9",
      "time": "8:00 am - 2:00 am",
      "event_location": "Auditorium D Block by Mr. Abdul Hameed"
    },
    {
      "event_name": "Admissions Activity",
      "date": "July 9",
      "time": "8:00 am - 2:00 am",
      "event_location": "Auditorium D Block by Mr. Abdul Hameed"
    },
    {
      "event_name": "CSO Event",
      "date": "July 9",
      "time": "2:00 pm - 6:00 pm",
      "event_location": "C-109 by Mr. Zain"
    },
    {
      "event_name": "Admissions Activity",
      "date": "July 10",
      "time": "8:00 am - 2:00 am",
      "event_location": "Auditorium D Block by Mr. Abdul Hameed"
    },
    {
      "event_name": "Admissions Activity",
      "date": "July 10",
      "time": "8:00 am - 2:00 am",
      "event_location": "Auditorium D Block by Mr. Abdul Hameed"
    },
    {
      "event_name": "MS Thesis Defense",
      "date": "July 10",
      "time": "3:00 pm - 4:00 pm",
      "event_location": "C-Block C109 By Babar Shahzad FSC"
    },
    {
      "event_name": "Admissions Activity",
      "date": "July 11",
      "time": "8:00 am - 2:00 am",
      "event_location": "Auditorium D Block by Mr. Abdul Hameed"
    },
    {
      "event_name": "PHD Admission Interviews",
      "date": "July 13",
      "time": "9:00 am - 2:00 pm",
      "event_location": "MEDC-117 by Ms. Fasiha"
    },
    {
      "event_name": "FSM Event",
      "date": "July 13",
      "time": "12:00 pm - 2:00 pm",
      "event_location": "Central Meeting Room by Ms. Fasiha"
    },
    {
      "event_name": "CSO Event",
      "date": "July 14",
      "time": "8:00 am - 6:00 pm",
      "event_location": "Auditorium by Ms. Laraib"
    },
    {
      "event_name": "Orientation 2026 Computing",
      "date": "August 10",
      "time": "8:00 am - 7:00 pm",
      "event_location": "Auditorium A and C Block by Dr. Hasan Mujtaba"
    },
    {
      "event_name": "Orientation 2026 Computing",
      "date": "August 11",
      "time": "8:00 am - 7:00 pm",
      "event_location": "Auditorium A and C Block by Dr. Hasan Mujtaba"
    },
    {
      "event_name": "Engineering Classes Series - FSE",
      "date": "August 17",
      "time": "2:00 pm - 5:00 pm",
      "event_location": "Auditorium A Block by Mr. Tariq"
    },
    {
      "event_name": "FSE Engineering Classes Series - II",
      "date": "August 20",
      "time": "2:00 pm - 5:00 pm",
      "event_location": "Auditorium D Block by Mr. Tariq"
    },
    {
      "event_name": "Engineering Classes Series - FSE",
      "date": "August 24",
      "time": "2:00 pm - 5:00 pm",
      "event_location": "Auditorium A Block by Mr. Tariq"
    },
    {
      "event_name": "FSE Engineering Classes Series - II",
      "date": "August 27",
      "time": "2:00 pm - 5:00 pm",
      "event_location": "Auditorium D Block by Mr. Tariq"
    },
    {
      "event_name": "Engineering Classes Series - FSE",
      "date": "August 31",
      "time": "2:00 pm - 5:00 pm",
      "event_location": "Auditorium A Block by Mr. Tariq"
    }
  ]
}